setup.py
Shimehari.egg-info/PKG-INFO
Shimehari.egg-info/SOURCES.txt
Shimehari.egg-info/dependency_links.txt
Shimehari.egg-info/not-zip-safe
Shimehari.egg-info/requires.txt
Shimehari.egg-info/top_level.txt
shimehari/__init__.py
shimehari/app.py
shimehari/cache.py
shimehari/configuration.py
shimehari/contexts.py
shimehari/controllers.py
shimehari/crypt.py
shimehari/helpers.py
shimehari/logging.py
shimehari/routing.py
shimehari/session.py
shimehari/shared.py
shimehari/testing.py
shimehari/wrappers.py
shimehari/core/__init__.py
shimehari/core/cachestore.py
shimehari/core/config.py
shimehari/core/exceptions.py
shimehari/core/helpers.py
shimehari/core/signals.py
shimehari/core/conf/__init__.py
shimehari/core/conf/config.org.py
shimehari/core/conf/controller_template.org.py
shimehari/core/conf/shimehari
shimehari/core/conf/app_template/__init__.py
shimehari/core/conf/app_template/main.py
shimehari/core/conf/app_template/router.py
shimehari/core/conf/app_template/controllers/__init__.py
shimehari/core/conf/app_template/controllers/index.py
shimehari/core/conf/app_template/models/__init__.py
shimehari/core/manage/AbstractCommand.py
shimehari/core/manage/__init__.py
shimehari/core/manage/commands/__init__.py
shimehari/core/manage/commands/checkconfig.py
shimehari/core/manage/commands/clean.py
shimehari/core/manage/commands/create.py
shimehari/core/manage/commands/drink.py
shimehari/core/manage/commands/generate.py
shimehari/core/manage/commands/help.py
shimehari/core/manage/commands/routes.py
shimehari/template/__init__.py
shimehari/template/jinja2/__init__.py
shimehari/template/jinja2/templating.py