Metadata-Version: 1.1
Name: Shimehari
Version: 0.1.10
Summary: moderate framework for Python. based on Werkzeug, Jinja2
Home-page: http://shimehari.hageee.net
Author: Yamaguchi Eikichi, Keiichiro Matsumoto
Author-email: megane@glasses-factory.net
License: BSD
Platform: any
Classifier: Development Status :: 2 - Pre-Alpha
Classifier: Environment :: Web Environment
Classifier: Intended Audience :: Developers
Classifier: License :: OSI Approved :: BSD License
Classifier: Operating System :: OS Independent
Classifier: Programming Language :: Python
Classifier: Programming Language :: Python :: 2.6
Classifier: Programming Language :: Python :: 2.7
Classifier: Topic :: Internet :: WWW/HTTP :: Dynamic Content
Classifier: Topic :: Software Development :: Libraries :: Python Modules
